kplugins/__init__.py
kplugins/async_utils.py
kplugins/config.py
kplugins/extensions.py
kplugins/get_sparameters_path.py
kplugins/materials.py
kplugins/plot.py
kplugins/port_symmetries.py
kplugins/typings.py
kplugins/kmeep/__init__.py
kplugins/kmeep/get_material.py
kplugins/kmeep/get_meep_geometry.py
kplugins/kmeep/get_port_eigenmode.py
kplugins/kmeep/get_simulation.py
kplugins/kmeep/get_simulation_grating_farfield.py
kplugins/kmeep/get_simulation_grating_fiber.py
kplugins/kmeep/meep_adjoint_optimization.py
kplugins/kmeep/test_eigenmode.py
kplugins/kmeep/test_materials.py
kplugins/kmeep/test_write_sparameters_meep.py
kplugins/kmeep/write_sparameters_grating.py
kplugins/kmeep/write_sparameters_meep.py
kplugins/kmeep/write_sparameters_meep_batch.py
kplugins/kmeep/write_sparameters_meep_mpi.py
kplugins/kmeep/test_sparameterNxN/test_sparameterNxN_crossing.csv
kplugins/kmeep/test_sparameterNxN/test_sparameterNxN_straight.csv
kplugins/kmeep/test_write_sparameters_meep/test_sparameterNxN_crossing.csv
kplugins/kmeep/test_write_sparameters_meep/test_sparameterNxN_straight.csv
kplugins/kmeep/test_write_sparameters_meep/test_sparameterNxN_symmetries_straight.csv
kplugins/kmeep/test_write_sparameters_meep/test_sparameter_straight_mpi.csv
kplugins/kmeep/test_write_sparameters_meep/test_sparameter_straight_mpi_pool.csv
kplugins/kmeep/test_write_sparameters_meep/test_sparameters_crossing_symmetric.csv
kplugins/kmeep/test_write_sparameters_meep/test_sparameters_straight.csv
kplugins/kmeep/test_write_sparameters_meep/test_sparameters_straight_batch.csv
kplugins/kmeep/test_write_sparameters_meep/test_sparameters_straight_mpi.csv
kplugins/kmeep/test_write_sparameters_meep/test_sparameters_straight_mpi_pool.csv
kplugins/kmeep/test_write_sparameters_meep/test_sparameters_straight_symmetric.csv
kplugins/lumerical/simulation_settings.py
kplugins/lumerical/write_sparameters_lumerical.py
kplugins-0.0.2.dist-info/LICENSE
kplugins-0.0.2.dist-info/WHEEL
kplugins-0.0.2.dist-info/METADATA
kplugins-0.0.2.dist-info/RECORD
